esma/__init__.py
esma/adiabatic.sh
esma/checks.py
esma/compute.py
esma/export.py
esma/generate.py
esma/kpoints.py
esma/ph.py
esma/ph_plot.py
esma/plot_band.py
esma/plot_sigma_energy.py
esma/plots.py
esma/project.py
esma/reads.py
esma/remote.py
esma/run.py
esma/scaffold.py
esma/slurm.py
esma/structure.py
esma/utils.py
esma/commands/wannier_stack.py
esma/configs/config.py
esma/configs/default.json
esma/inputs/generic.py
esma/inputs/matdyn.py
esma/inputs/plotband.py
esma/inputs/pw.py
esma/inputs/pw2wannier90.py
esma/inputs/wannier90.py
esma/inputs/writes.py
esma/plotting/kdos.py
esma/seekpath/__init__.py
esma/seekpath/getpaths.py
esma/seekpath/util.py
esma/seekpath/brillouinzone/__init__.py
esma/seekpath/brillouinzone/brillouinzone.py
esma/seekpath/hpkot/__init__.py
esma/seekpath/hpkot/spg_db.py
esma/seekpath/hpkot/spg_mapping.py
esma/seekpath/hpkot/tools.py
esma/seekpath/hpkot/band_path_data/aP2/POSCAR_inversion
esma/seekpath/hpkot/band_path_data/aP2/POSCAR_noinversion
esma/seekpath/hpkot/band_path_data/aP2/k_vector_parameters.txt
esma/seekpath/hpkot/band_path_data/aP2/path.txt
esma/seekpath/hpkot/band_path_data/aP2/points.txt
esma/seekpath/hpkot/band_path_data/aP3/POSCAR_inversion
esma/seekpath/hpkot/band_path_data/aP3/POSCAR_noinversion
esma/seekpath/hpkot/band_path_data/aP3/k_vector_parameters.txt
esma/seekpath/hpkot/band_path_data/aP3/path.txt
esma/seekpath/hpkot/band_path_data/aP3/points.txt
esma/seekpath/hpkot/band_path_data/cF1/POSCAR_inversion
esma/seekpath/hpkot/band_path_data/cF1/POSCAR_noinversion
esma/seekpath/hpkot/band_path_data/cF1/k_vector_parameters.txt
esma/seekpath/hpkot/band_path_data/cF1/path.txt
esma/seekpath/hpkot/band_path_data/cF1/points.txt
esma/seekpath/hpkot/band_path_data/cF2/POSCAR_inversion
esma/seekpath/hpkot/band_path_data/cF2/POSCAR_noinversion
esma/seekpath/hpkot/band_path_data/cF2/k_vector_parameters.txt
esma/seekpath/hpkot/band_path_data/cF2/path.txt
esma/seekpath/hpkot/band_path_data/cF2/points.txt
esma-0.0.502.dist-info/LICENSE
esma-0.0.502.dist-info/METADATA
esma-0.0.502.dist-info/WHEEL
esma-0.0.502.dist-info/top_level.txt
esma-0.0.502.dist-info/RECORD
